projbuild/__init__.py
projbuild/main.py
projbuild/runner.py
projbuild-0.1.0.dist-info/LICENSE
projbuild-0.1.0.dist-info/METADATA
projbuild-0.1.0.dist-info/WHEEL
projbuild-0.1.0.dist-info/entry_points.txt
projbuild-0.1.0.dist-info/top_level.txt
projbuild-0.1.0.dist-info/RECORD
